controller.v
module controller(
    input [6:0] opcode,
    input [2:0] funct3,
    input funct7_5,
    output reg [3:0] alu_control,
    output reg [2:0] sel_ext,
    output reg sel_alu_src_b,
    output reg rf_we,
    output reg dmem_we,
    output reg [1:0] sel_result);

    reg [1:0] alu_op;

    //first level decoder
    always @(*) begin
        alu_op = 2'b00;
        sel_ext = 3'b000;
        sel_alu_src_b = 1'b0;
        rf_we = 1'b0;
        dmem_we = 1'b0;
        sel_result = 2'b00;
        
        case (opcode)
            7'b0110011: begin //R-type
                alu_op = 2'b01;
                rf_we = 1'b1;
            end
            7'b0010011: begin //I-type
                alu_op = 2'b10;
                sel_alu_src_b = 1'b1;
                rf_we = 1'b1;
            end
            7'b0000011: begin //Load
                alu_op = 2'b00;
                sel_alu_src_b = 1'b1;
                sel_ext = 3'b000;
                rf_we = 1'b1;
                sel_result = 2'b01; //Select data memory
            end
            7'b0100011: begin //Store
                alu_op = 2'b00;
                sel_alu_src_b = 1'b1;
                sel_ext = 3'b001;
                dmem_we = 1'b1;
            end
            7'b1100011: begin //Branch
                alu_op = 2'b01; //Use SUB for comparison
                sel_ext = 3'b010;
                sel_alu_src_b = 1'b0; //Compare two registers (rs1 - rs2)
            end
            7'b1101111: begin //JAL
                alu_op = 2'b00;
                sel_ext = 3'b100;
                rf_we = 1'b1;
                sel_result = 2'b10; //Select PC+4
            end
            7'b0110111: begin //LUI
                sel_ext = 3'b011;      // U-type format
                rf_we = 1'b1;          // Write to register
                sel_result = 2'b11;    // Select sign extender output directly (bypass ALU)
            end
            default: begin
                //NOP or unsupported instruction
                
            end
        endcase
    end

    //second level decoder
    always @(*)begin
        alu_control = 4'b0000; //default NOP
        case (alu_op)
            2'b00: begin //Load/Store/JAL
                alu_control = 4'b0010; //ADD
            end
            2'b01: begin //R-type and Branch
                // For branches (opcode 1100011), always use SUB to set Zero flag
                if (opcode == 7'b1100011) begin
                    alu_control = 4'b0110; //SUB for all branches
                end else begin
                    // R-type instructions
                    case ({funct7_5, funct3})
                        4'b0000: alu_control = 4'b0010; //ADD
                        4'b1000: alu_control = 4'b0110; //SUB
                        4'b0111: alu_control = 4'b1110; //AND
                        4'b0110: alu_control = 4'b0001; //OR
                        4'b0100: alu_control = 4'b0011; //XOR
                        4'b0001: alu_control = 4'b0100; //SLL
                        4'b0101: alu_control = 4'b0101; //SRL
                        4'b1101: alu_control = 4'b1000; //SRA
                        4'b0010: alu_control = 4'b0111; //SLT
                        default: alu_control = 4'b0000; //NOP
                    endcase
                end
            end
            2'b10: begin //I-type
                case (funct3)
                    3'b000: alu_control = 4'b0010; //ADD (ADDI)
                    3'b111: alu_control = 4'b1110; //AND (ANDI)
                    3'b110: alu_control = 4'b0001; //OR (ORI)
                    3'b100: alu_control = 4'b0011; //XOR (XORI)
                    3'b001: alu_control = 4'b0100; //SLL (SLLI)
                    3'b101: begin
                        if (funct7_5 == 1'b0)
                            alu_control = 4'b0101; //SRL (SRLI)
                        else
                            alu_control = 4'b1000; //SRA (SRAI)
                    end
                    3'b010: alu_control = 4'b0111; //SLT (SLTI)
                    default: alu_control = 4'b0000; //NOP
                endcase
            end
            2'b11: begin //LUI (pass-through B)
                alu_control = 4'b1111; //Pass-through
            end
            default: begin
                alu_control = 4'b0000; //NOP
            end
        endcase
    end
endmodule

data_mem.v
//Data memory module
module data_mem(
    input clk,
    input reset_n,
    input we,
    input [31:0] addr,
    input [31:0] wd,
    output [31:0] rd
    );

    //making memory
    reg [31:0] memory [0:31]; //mem consists of 32 registers each 32 bit wide
    integer k;

    //read operation
    assign rd = memory[addr]; //assign what is placed at memory address to rd

    always @(posedge clk or negedge reset_n) begin
        if (~reset_n) begin
            // Clear all memory on reset
            for (k = 0; k < 32; k = k + 1) begin
                memory[k] <= 32'h00000000;
            end
        end else if (we) begin
            //write operation
            memory[addr] <= wd;
        end
    end
endmodule

alu.v
module alu(
    input [31:0] A,
    input [31:0] B,
    input [3:0] alu_control,
    output reg [31:0] alu_out,
    output reg Zero
    );

    always @(*) begin
        case (alu_control)
        
            4'b0001: begin
                alu_out = A | B;               //OR
            end
            4'b0010: begin
                alu_out = A + B;               //ADD
            end
            4'b0011: begin
                alu_out = A ^ B;               //XOR
            end
            4'b0100: begin
                alu_out = A << B[4:0];         //SLL
            end
            4'b0101: begin
                alu_out = A >> B[4:0];        //SRL
            end
            4'b0110: begin
                alu_out = A - B;               //SUB
            end
            4'b0111: begin
                alu_out = (A < B) ? 32'b1 : 32'b0; //SLT
            end
            4'b1000: begin
                alu_out = A >>> B[4:0];       //SRA
            end
            4'b1100: begin
                alu_out = ~(A | B);            //NOR
            end
            4'b1110: begin
                alu_out = A & B;               //AND
            end
            4'b1111: begin
                alu_out = B;                   //Pass-through B (for LUI)
            end
            default: begin
                alu_out = 32'b0;
            end
        endcase

        //Set Zero flag
        if (alu_out == 32'b0)
            Zero = 1'b1;
        else
            Zero = 1'b0;
    end

endmodule

multiplexer.v
//mutiplexer module for immediate selection
module mux1(sel, A1, B1, mux_out);
    input sel;
    input [31:0] A1, B1;
    output [31:0] mux_out;

    assign mux_out = (sel == 1'b0)? A1 : B1;
endmodule

//multiplexer module for register file write address selection
module mux2(sel, A2, B2, mux_out2);
    input sel;
    input [4:0] A2, B2;
    output [4:0] mux_out2;

    assign mux_out2 = (sel == 1'b0)? A2 : B2;
endmodule

sign_extender.v
module sign_extender(
    input [2:0] sel_ext,
    input [31:7] in,
    output reg [31:0] out
    );

    //gonna assume negative numbers are in 2's complement

    always @(*) begin
        case (sel_ext)
            3'b000: begin //I-type: 12 bit immediate
                out = {{20{in[31]}}, in[31:20]}; //{a,b} is concatenation so result is a 32 bit value with a followed by b
            end
            3'b001: begin //S-type: 12 bit immediate
                out = {{20{in[31]}}, in[31:25], in[11:7]}; //{20{in[31]}} replicates the sign bit 20 times
            end
            3'b010: begin //B-type: 13 bit immediate
                out = {{19{in[31]}}, in[31], in[7], in[30:25], in[11:8], 1'b0};
            end
            3'b011: begin //U-type: 20 bit immediate
                out = {in[31:12], 12'b0};
            end
            3'b100: begin //J-type: 21 bit immediate
                out = {{11{in[31]}}, in[31], in[19:12], in[20], in[30:21], 1'b0};
            end
            default: begin
                out = 32'b0;
            end
        endcase
    end
endmodule

reg_file.v
module regfile(
    input clk,
    input reset_n,
    input we,
    input [4:0] a1,
    input [4:0] a2,
    input [4:0] a3,
    input [31:0] wd,
    output [31:0] rd1,
    output [31:0] rd2
    );

    reg [31:0] registers [0:31];
    integer k;

    assign rd1 = registers[a1];
    assign rd2 = registers[a2];

    always @(posedge clk or negedge reset_n) begin
        if (~reset_n) begin
            // Clear all registers on reset
            for (k = 0; k < 32; k = k + 1) begin
                registers[k] <= 32'h00000000;
            end
        end else if (we) begin
            registers[a3] <= wd;
        end
    end
endmodule

instr_mem.v
module instruction_mem(
    read_address, instr_out
);

    input [31:0] read_address;
    output [31:0] instr_out;

    //making memory
    reg [31:0] memory [0:31]; //mem consists of 32 registers each 32 bit wide

    assign instr_out = memory[read_address[31:2]]; //Divide byte address by 4 to get word address

    
endmodule

program_counter.v
//PC counter works like this -> new instruction...Pc + 4
module program_counter(
    input clk,
    input [31:0] present_val,
    input load_en,
    input reset_n,
    output reg [31:0] pc_out
);

    wire[31:0] sum; 

    always@(posedge clk or negedge reset_n)
    begin
        if (~reset_n)begin
            pc_out <= 32'h00000000;
        end   else begin
            pc_out <= present_val; // present_val is already PC+4 or branch target
        end
    end

endmodule

top_module_sc.v
//top module is where all the submodules are instantiated like a testbench
`include "program_counter.v"
`include "instr_mem.v"
`include "reg_file.v"
`include "data_mem.v"
`include "alu.v"
`include "controller.v"
`include "sign_extender.v"
`include "multiplexer.v"
module riscv_single_cycle(
    input clk,
    input reset

);
    wire [31:0] pc_out;
    wire [31:0] instr_out;
    wire [31:0] mux_out1;
    wire [31:0] mux_out2;
    wire [31:0] alu_out;
    wire [31:0] rd1;
    wire [31:0] rd2;    
    wire [31:0] rd;
    wire [3:0] alu_control;
    wire [2:0] sel_ext;
    wire [31:0] se_out;
    wire sel_alu_src_b;
    wire rf_we;
    wire dmem_we;
    wire [1:0] sel_result;
    wire Zero;

    // PC + 4 calculation
    wire [31:0] pc_plus_4;
    assign pc_plus_4 = pc_out + 32'd4;

    // Branch logic
    wire branch_taken;
    assign branch_taken = (instr_out[6:0] == 7'b1100011) && Zero; // Branch opcode AND Zero flag

    wire [31:0] pc_target;
    assign pc_target = pc_out + se_out; // PC + branch/jump offset

    wire [31:0] pc_next;
    assign pc_next = branch_taken ? pc_target : pc_plus_4;

    //Instantiate Program Counter
    program_counter PC ( .clk(clk),
                         .present_val(pc_next),
                         .load_en(branch_taken),
                         .reset_n(reset),
                         .pc_out(pc_out)
                       );

    
    //Instantiate Instruction Memory
    instruction_mem IM (.read_address(pc_out),
                   .instr_out(instr_out)
                 );

    // 4-input mux for register write data
    reg [31:0] result_to_rf;
    always @(*) begin
        case (sel_result)
            2'b00: result_to_rf = alu_out;      // ALU result (normal ops)
            2'b01: result_to_rf = rd;           // Data memory (loads)
            2'b10: result_to_rf = pc_plus_4;    // PC+4 (JAL)
            2'b11: result_to_rf = se_out;       // Sign extender (LUI)
            default: result_to_rf = alu_out;
        endcase
    end

    //Instantiate register File
    regfile RF ( .clk(clk),
                     .reset_n(reset),
                     .we(rf_we),
                     .a1(instr_out[19:15]),
                     .a2(instr_out[24:20]),
                     .a3(instr_out[11:7]),
                     .wd(result_to_rf),          // Write data selected by mux
                     .rd1(rd1),
                     .rd2(rd2)
                   );

    //Instantiate Sign Extender
    sign_extender SE ( .sel_ext(sel_ext),
                       .in(instr_out[31:7]),
                       .out(se_out)
                     );
                    
    //Instantiate ALU Mux
    mux1 ALU_MUX ( .sel(sel_alu_src_b),
                        .A1(rd2),
                        .B1(se_out),
                        .mux_out(mux_out1)
                    );

    //Instantiate ALU
    alu ALU_UNIT ( .A(rd1),
                   .B(mux_out1),
                   .alu_control(alu_control),
                   .alu_out(alu_out),
                   .Zero(Zero)
                 );

    //Instantiate Data Memory
    data_mem DM ( .clk(clk),
                  .reset_n(reset),
                  .we(dmem_we),
                  .addr(alu_out),
                  .wd(rd2),
                  .rd(rd)
                );

    //Instantiate Controller
    controller CTRL ( .opcode(instr_out[6:0]),
                      .funct3(instr_out[14:12]),
                      .funct7_5(instr_out[30]),
                      .alu_control(alu_control),
                      .sel_ext(sel_ext),
                      .sel_alu_src_b(sel_alu_src_b),
                      .rf_we(rf_we),
                      .dmem_we(dmem_we),
                      .sel_result(sel_result)
                    );

endmodule

top_module_tb.v
`include "top_module_sc.v"
`timescale 1ns / 1ps

module top_module_tb;
    reg clk;
    reg reset;

    // Instantiate the top module
    riscv_single_cycle DUT (
        .clk(clk),
        .reset(reset)
    );

    // Clock generation
    initial begin
        clk = 0;
        forever #5 clk = ~clk; // 10ns period
    end

    // Test sequence
    initial begin
        $dumpfile("top_module_tb.vcd");
        $dumpvars(0, top_module_tb);

        // Load test instructions BEFORE reset
        $readmemh("instructions.hex", DUT.IM.memory);
        
        // Debug: Check if instructions loaded
        $display("Loaded instructions:");
        $display("mem[0] = %h", DUT.IM.memory[0]);
        $display("mem[1] = %h", DUT.IM.memory[1]);
        $display("mem[2] = %h", DUT.IM.memory[2]);

        // Apply reset (active low)
        reset = 0;
        #15; // Hold reset for 1.5 clock cycles
        reset = 1; // Release reset
        
        // Debug: Check after reset
        $display("\nAfter reset:");
        $display("mem[0] = %h", DUT.IM.memory[0]);
        $display("mem[1] = %h", DUT.IM.memory[1]);
        $display("PC = %h", DUT.pc_out);

        $display("\n=== Starting RISC-V Processor Test ===\n");

        // Run for enough cycles to execute all instructions
        repeat(20) begin
            #1; // Small delay to see stable values
            $display("PC=%h | Instr=%h | alu_ctrl=%b | alu_out=%h | wd=%h | x1=%d x2=%d x3=%d x4=%d x5=%d", 
                     DUT.pc_out, DUT.instr_out, DUT.alu_control, DUT.alu_out, DUT.result_to_rf,
                     DUT.RF.registers[1], DUT.RF.registers[2], DUT.RF.registers[3], 
                     DUT.RF.registers[4], DUT.RF.registers[5]);
            @(posedge clk);
        end

        $display("\n=== Final Register State ===");
        $display("x1 = %d (Expected: 5)", DUT.RF.registers[1]);
        $display("x2 = %d (Expected: 10)", DUT.RF.registers[2]);
        $display("x3 = %d (Expected: 15)", DUT.RF.registers[3]);
        $display("x4 = %d (Expected: 5)", DUT.RF.registers[4]);
        $display("x5 = %h (Expected: 0)", DUT.RF.registers[5]);
        $display("x6 = %h (Expected: F)", DUT.RF.registers[6]);
        $display("x7 = %d (Expected: 5)", DUT.RF.registers[7]);
        $display("x8 = %d (Expected: 0, should be skipped)", DUT.RF.registers[8]);
        $display("x9 = %d (Expected: 77)", DUT.RF.registers[9]);

        $display("\n=== Memory State ===");
        $display("Data Memory[0] = %h (Expected: 00000005)", DUT.DM.memory[0]);

        $finish;
    end
endmodule

top_module_tb.vcd
$date
	Sun Dec 07 17:44:21 2025
$end
$version
	Icarus Verilog
$end
$timescale
	1ps
$end
$scope module top_module_tb $end
$var reg 1 ! clk $end
$var reg 1 " reset $end
$scope module DUT $end
$var wire 1 # branch_taken $end
$var wire 1 ! clk $end
$var wire 1 " reset $end
$var wire 2 $ sel_result [1:0] $end
$var wire 3 % sel_ext [2:0] $end
$var wire 1 & sel_alu_src_b $end
$var wire 32 ' se_out [31:0] $end
$var wire 1 ( rf_we $end
$var wire 32 ) rd2 [31:0] $end
$var wire 32 * rd1 [31:0] $end
$var wire 32 + rd [31:0] $end
$var wire 32 , pc_target [31:0] $end
$var wire 32 - pc_plus_4 [31:0] $end
$var wire 32 . pc_out [31:0] $end
$var wire 32 / pc_next [31:0] $end
$var wire 32 0 mux_out1 [31:0] $end
$var wire 32 1 instr_out [31:0] $end
$var wire 1 2 dmem_we $end
$var wire 32 3 alu_out [31:0] $end
$var wire 4 4 alu_control [3:0] $end
$var wire 1 5 Zero $end
$var reg 32 6 result_to_rf [31:0] $end
$scope module ALU_MUX $end
$var wire 1 & sel $end
$var wire 32 7 mux_out [31:0] $end
$var wire 32 8 B1 [31:0] $end
$var wire 32 9 A1 [31:0] $end
$upscope $end
$scope module ALU_UNIT $end
$var wire 32 : B [31:0] $end
$var wire 4 ; alu_control [3:0] $end
$var wire 32 < A [31:0] $end
$var reg 1 5 Zero $end
$var reg 32 = alu_out [31:0] $end
$upscope $end
$scope module CTRL $end
$var wire 3 > funct3 [2:0] $end
$var wire 1 ? funct7_5 $end
$var wire 7 @ opcode [6:0] $end
$var reg 4 A alu_control [3:0] $end
$var reg 2 B alu_op [1:0] $end
$var reg 1 2 dmem_we $end
$var reg 1 ( rf_we $end
$var reg 1 & sel_alu_src_b $end
$var reg 3 C sel_ext [2:0] $end
$var reg 2 D sel_result [1:0] $end
$upscope $end
$scope module DM $end
$var wire 32 E addr [31:0] $end
$var wire 1 ! clk $end
$var wire 32 F rd [31:0] $end
$var wire 1 " reset_n $end
$var wire 1 2 we $end
$var wire 32 G wd [31:0] $end
$var integer 32 H k [31:0] $end
$upscope $end
$scope module IM $end
$var wire 32 I instr_out [31:0] $end
$var wire 32 J read_address [31:0] $end
$upscope $end
$scope module PC $end
$var wire 1 ! clk $end
$var wire 1 # load_en $end
$var wire 32 K present_val [31:0] $end
$var wire 1 " reset_n $end
$var reg 32 L pc_out [31:0] $end
$upscope $end
$scope module RF $end
$var wire 5 M a1 [4:0] $end
$var wire 5 N a2 [4:0] $end
$var wire 5 O a3 [4:0] $end
$var wire 1 ! clk $end
$var wire 32 P rd1 [31:0] $end
$var wire 32 Q rd2 [31:0] $end
$var wire 1 " reset_n $end
$var wire 32 R wd [31:0] $end
$var wire 1 ( we $end
$var integer 32 S k [31:0] $end
$upscope $end
$scope module SE $end
$var wire 25 T in [31:7] $end
$var wire 3 U sel_ext [2:0] $end
$var reg 32 V out [31:0] $end
$upscope $end
$upscope $end
$upscope $end
$enddefinitions $end
$comment Show the parameter values. $end
$dumpall
$end
#0
$dumpvars
b101 V
b0 U
b1010000000000001 T
b100000 S
b101 R
b0 Q
b0 P
b1 O
b101 N
b0 M
b0 L
b100 K
b0 J
b10100000000000010010011 I
b100000 H
b0 G
b0 F
b101 E
b0 D
b0 C
b10 B
b10 A
b10011 @
0?
b0 >
b101 =
b0 <
b10 ;
b101 :
b0 9
b101 8
b101 7
b101 6
05
b10 4
b101 3
02
b10100000000000010010011 1
b101 0
b100 /
b0 .
b100 -
b101 ,
b0 +
b0 *
b0 )
1(
b101 '
1&
b0 %
b0 $
0#
0"
0!
$end
#5000
b100000 H
b100000 S
1!
#10000
0!
#15000
b1010 6
b1010 R
b1010 3
b1010 =
b1010 E
b1010 0
b1010 7
b1010 :
b1010 '
b1010 8
b1010 V
b10100000000000010 T
b10 O
b1010 N
b101000000000000100010011 1
b101000000000000100010011 I
b1000 /
b1000 K
b1110 ,
b1000 -
b100 .
b100 J
b100 L
1!
1"
#20000
0!
#25000
b1010 0
b1010 7
b1010 :
b1111 6
b1111 R
b1111 3
b1111 =
b1111 E
b10 4
b10 ;
b10 A
1(
0&
b1 B
b10 '
b10 8
b10 V
b1010 )
b1010 9
b1010 G
b1010 Q
b101 *
b101 <
b101 P
b110011 @
b100000100000011 T
b11 O
b10 N
b1 M
b1000001000000110110011 1
b1000001000000110110011 I
b1100 /
b1100 K
b1010 ,
b1100 -
b1000 .
b1000 J
b1000 L
1!
#30000
0!
#35000
b101 6
b101 R
b101 0
b101 7
b101 :
05
b101 3
b101 =
b101 E
b110 4
b110 ;
b110 A
b10000000001 '
b10000000001 8
b10000000001 V
b101 )
b101 9
b101 G
b101 Q
b1010 *
b1010 <
b1010 P
1?
b100000000010001000000100 T
b100 O
b1 N
b10 M
b1000000000100010000001000110011 1
b1000000000100010000001000110011 I
b10000 /
b10000 K
b10000001101 ,
b10000 -
b1100 .
b1100 J
b1100 L
1!
#40000
0!
#45000
b0 6
b0 R
15
b0 3
b0 =
b0 E
b1010 0
b1010 7
b1010 :
b1110 4
b1110 ;
b1110 A
b10 '
b10 8
b10 V
b1010 )
b1010 9
b1010 G
b1010 Q
b101 *
b101 <
b101 P
0?
b111 >
b100000111100101 T
b101 O
b10 N
b1 M
b1000001111001010110011 1
b1000001111001010110011 I
b10100 /
b10100 K
b10010 ,
b10100 -
b10000 .
b10000 J
b10000 L
1!
#50000
0!
#55000
b1111 6
b1111 R
05
b1111 3
b1111 =
b1111 E
b1 4
b1 ;
b1 A
b110 >
b100000111000110 T
b110 O
b1000001110001100110011 1
b1000001110001100110011 I
b11000 /
b11000 K
b10110 ,
b11000 -
b10100 .
b10100 J
b10100 L
1!
#60000
0!
#65000
15
b0 6
b0 R
b0 0
b0 7
b0 :
b0 3
b0 =
b0 E
b10 4
b10 ;
b10 A
12
b1 %
b1 C
b1 U
1&
0(
b0 B
b0 '
b0 8
b0 V
b101 )
b101 9
b101 G
b101 Q
b0 *
b0 <
b0 P
b10 >
b100011 @
b10000001000000 T
b0 O
b1 N
b0 M
b100000010000000100011 1
b100000010000000100011 I
b11100 /
b11100 K
b11000 ,
b11100 -
b11000 .
b11000 J
b11000 L
1!
#70000
0!
#75000
15
b0 3
b0 =
b0 E
b0 0
b0 7
b0 :
b101 6
b101 R
b10 4
b10 ;
b10 A
b1 $
b1 D
1(
02
1&
b0 %
b0 C
b0 U
b0 '
b0 8
b0 V
b0 )
b0 9
b0 G
b0 Q
b11 @
b1000111 T
b111 O
b0 N
b10001110000011 1
b10001110000011 I
b100000 /
b100000 K
b11100 ,
b100000 -
b11100 .
b11100 J
b11100 L
b101 +
b101 F
1!
#80000
0!
#85000
b0 6
b0 R
b101 0
b101 7
b101 :
15
b101 +
b101 F
b0 3
b0 =
b0 E
b110 4
b110 ;
b110 A
b10 %
b10 C
b10 U
b1 B
b0 $
b0 D
0(
0&
b1000 '
b1000 8
b1000 V
b101 )
b101 9
b101 G
b101 Q
b101 *
b101 <
b101 P
1#
b0 >
b1100011 @
b10000100001000 T
b1000 O
b1 N
b1 M
b100001000010001100011 1
b100001000010001100011 I
b101000 /
b101000 K
b101000 ,
b100100 -
b100000 .
b100000 J
b100000 L
1!
#90000
0!
#95000
b1001101 6
b1001101 R
b1001101 0
b1001101 7
b1001101 :
05
bx +
bx F
b1001101 3
b1001101 =
b1001101 E
b10 4
b10 ;
b10 A
1(
1&
b0 %
b0 C
b0 U
b10 B
b1001101 '
b1001101 8
b1001101 V
b0 )
b0 9
b0 G
b0 Q
b0 *
b0 <
b0 P
0#
b10011 @
b10011010000000001001 T
b1001 O
b1101 N
b0 M
b100110100000000010010010011 1
b100110100000000010010010011 I
b101100 /
b101100 K
b1110101 ,
b101100 -
b101000 .
b101000 J
b101000 L
1!
#100000
0!
#105000
bx 0
bx 7
bx :
bx 6
bx R
bx 3
bx =
bx E
b10 4
b10 ;
b10 A
0(
0&
b0 B
bx '
bx 8
bx V
bx )
bx 9
bx G
bx Q
bx *
bx <
bx P
x?
bx >
bx @
bx T
bx O
bx N
bx M
bx 1
bx I
b110000 /
b110000 K
bx ,
b110000 -
b101100 .
b101100 J
b101100 L
1!
#110000
0!
#115000
b110100 /
b110100 K
b110100 -
b110000 .
b110000 J
b110000 L
1!
#120000
0!
#125000
b111000 /
b111000 K
b111000 -
b110100 .
b110100 J
b110100 L
1!
#130000
0!
#135000
b111100 /
b111100 K
b111100 -
b111000 .
b111000 J
b111000 L
1!
#140000
0!
#145000
b1000000 /
b1000000 K
b1000000 -
b111100 .
b111100 J
b111100 L
1!
#150000
0!
#155000
b1000100 /
b1000100 K
b1000100 -
b1000000 .
b1000000 J
b1000000 L
1!
#160000
0!
#165000
b1001000 /
b1001000 K
b1001000 -
b1000100 .
b1000100 J
b1000100 L
1!
#170000
0!
#175000
b1001100 /
b1001100 K
b1001100 -
b1001000 .
b1001000 J
b1001000 L
1!
#180000
0!
#185000
b1010000 /
b1010000 K
b1010000 -
b1001100 .
b1001100 J
b1001100 L
1!
#190000
0!
#195000
b1010100 /
b1010100 K
b1010100 -
b1010000 .
b1010000 J
b1010000 L
1!
#200000
0!
#205000
b1011000 /
b1011000 K
b1011000 -
b1010100 .
b1010100 J
b1010100 L
1!
#210000
0!
#215000
b1011100 /
b1011100 K
b1011100 -
b1011000 .
b1011000 J
b1011000 L
1!
