Single_Processor/alu.v
module alu(
    input [31:0] A,
    input [31:0] B,
    input [3:0] alu_control,
    output reg [31:0] alu_out,
    output reg Zero
    );

    always @(*) begin
        case (alu_control)
        
            4'b0001: begin
                alu_out = A | B;               //OR
            end
            4'b0010: begin
                alu_out = A + B;               //ADD
            end
            4'b0011: begin
                alu_out = A ^ B;               //XOR
            end
            4'b0100: begin
                alu_out = A << B[4:0];         //SLL
            end
            4'b0101: begin
                alu_out = A >> B[4:0];        //SRL
            end
            4'b0110: begin
                alu_out = A - B;               //SUB
            end
            4'b0111: begin
                alu_out = (A < B) ? 32'b1 : 32'b0; //SLT
            end
            4'b1000: begin
                alu_out = A >>> B[4:0];       //SRA
            end
            4'b1100: begin
                alu_out = ~(A | B);            //NOR
            end
            4'b1110: begin
                alu_out = A & B;               //AND
            end
            4'b1111: begin
                alu_out = B;                   //Pass-through B (for LUI)
            end
            default: begin
                alu_out = 32'b0;
            end
        endcase

        //Set Zero flag
        if (alu_out == 32'b0)
            Zero = 1'b1;
        else
            Zero = 1'b0;
    end

endmodule

Single_Processor/testbenches/alu_tb.v
`include "../alu.v"
`timescale 1ns / 1ps
module alu_tb;
    reg [31:0] operand_a;
    reg [31:0] operand_b;
    reg [3:0] alu_control;
    wire [31:0] alu_result;
    wire zero_flag;

    // Instantiate the ALU module
    alu ALU (
        .A(operand_a),
        .B(operand_b),
        .alu_control(alu_control),
        .alu_out(alu_result),
        .Zero(zero_flag)
    );

    task init();
        begin
        // Initialize signals
        operand_a = 0;
        operand_b = 0;
        alu_control = 0;
        end   
    endtask

    initial begin
        $dumpfile("alu_tb.vcd");
        $dumpvars(0, alu_tb);

        init();

        // Test Case 1: Addition
        operand_a = 32'h00000005;
        operand_b = 32'h00000003;
        alu_control = 4'b0010; // ADD
        #10; // Wait for output to stabilize
        $display("Test Case 1 (ADD) - Result: %h (Expected: 00000008)", alu_result);

        // Test Case 2: Subtraction
        operand_a = 32'h00000005;
        operand_b = 32'h00000003;
        alu_control = 4'b0110; // SUB
        #10; // Wait for output to stabilize
        $display("Test Case 2 (SUB) - Result: %h (Expected: 00000002)", alu_result);

        // Test Case 3: AND
        operand_a = 32'h0000000F;
        operand_b = 32'h00000003;
        alu_control = 4'b1110; // AND
        #10; // Wait for output to stabilize
        $display("Test Case 3 (AND) - Result: %h (Expected: 00000003)", alu_result);

        // Test Case 4: OR
        operand_a = 32'h0000000C;
        operand_b = 32'h00000003;
        alu_control = 4'b0001; // OR
        #10;
        $display("Test Case 4 (OR) - Result: %h (Expected: 0000000F)", alu_result);

        // Test Case 5: XOR
        operand_a = 32'h0000000F;
        operand_b = 32'h00000003;
        alu_control = 4'b0011; // XOR
        #10;
        $display("Test Case 5 (XOR) - Result: %h (Expected: 0000000C)", alu_result);

        // Test Case 6: SLL (Shift Left Logical)
        operand_a = 32'h00000001;
        operand_b = 32'h00000004;
        alu_control = 4'b0100; // SLL
        #10;
        $display("Test Case 6 (SLL) - Result: %h (Expected: 00000010)", alu_result);

        // Test Case 7: SRL (Shift Right Logical)
        operand_a = 32'h00000010;
        operand_b = 32'h00000002;
        alu_control = 4'b0101; // SRL
        #10;
        $display("Test Case 7 (SRL) - Result: %h (Expected: 00000004)", alu_result);

        // Test Case 8: SLT (Set Less Than)
        operand_a = 32'h00000002;
        operand_b = 32'h00000005;
        alu_control = 4'b0111; // SLT
        #10;
        $display("Test Case 8 (SLT) - Result: %h (Expected: 00000001)", alu_result);

        $finish;
    end
endmodule

Single_Processor/testbenches/alu_tb.vcd
$date
	Sat Dec 06 17:40:46 2025
$end
$version
	Icarus Verilog
$end
$timescale
	1ps
$end
$scope module alu_tb $end
$var wire 1 ! zero_flag $end
$var wire 32 " alu_result [31:0] $end
$var reg 4 # alu_control [3:0] $end
$var reg 32 $ operand_a [31:0] $end
$var reg 32 % operand_b [31:0] $end
$scope module ALU $end
$var wire 32 & A [31:0] $end
$var wire 32 ' B [31:0] $end
$var wire 4 ( alu_control [3:0] $end
$var reg 1 ! Zero $end
$var reg 32 ) alu_out [31:0] $end
$upscope $end
$scope task init $end
$upscope $end
$upscope $end
$enddefinitions $end
$comment Show the parameter values. $end
$dumpall
$end
#0
$dumpvars
b1000 )
b10 (
b11 '
b101 &
b11 %
b101 $
b10 #
b1000 "
0!
$end
#10000
b10 "
b10 )
b110 #
b110 (
#20000
b11 "
b11 )
b1110 #
b1110 (
b1111 $
b1111 &
#30000
b1111 "
b1111 )
b1 #
b1 (
b1100 $
b1100 &
#40000
b1100 "
b1100 )
b11 #
b11 (
b1111 $
b1111 &
#50000
b10000 "
b10000 )
b100 #
b100 (
b100 %
b100 '
b1 $
b1 &
#60000
b100 "
b100 )
b101 #
b101 (
b10 %
b10 '
b10000 $
b10000 &
#70000
b1 "
b1 )
b111 #
b111 (
b101 %
b101 '
b10 $
b10 &
